.gitignore
.gitmodules
CMakeLists.txt
LICENSE.md
README.md
pyproject.toml
setup.py
_skbuild/linux-x86_64-3.8/cmake-install/ggml/libggml.so
_skbuild/linux-x86_64-3.8/cmake-install/lib/libggml.so
ggml/__init__.py
ggml/experimental.py
ggml/ggml.py
ggml_python.egg-info/PKG-INFO
ggml_python.egg-info/SOURCES.txt
ggml_python.egg-info/dependency_links.txt
ggml_python.egg-info/requires.txt
ggml_python.egg-info/top_level.txt
tests/test_experimental.py
tests/test_ggml.py
vendor/ggml/.gitignore
vendor/ggml/CMakeLists.txt
vendor/ggml/LICENSE
vendor/ggml/README.md
vendor/ggml/cmake/BuildTypes.cmake
vendor/ggml/cmake/GitVars.cmake
vendor/ggml/examples/CMakeLists.txt
vendor/ggml/examples/dr_wav.h
vendor/ggml/examples/gpt-2/CMakeLists.txt
vendor/ggml/examples/gpt-2/README.md
vendor/ggml/examples/gpt-2/convert-cerebras-to-ggml.py
vendor/ggml/examples/gpt-2/convert-ckpt-to-ggml.py
vendor/ggml/examples/gpt-2/convert-h5-to-ggml.py
vendor/ggml/examples/gpt-2/download-ggml-model.sh
vendor/ggml/examples/gpt-2/download-model.sh
vendor/ggml/examples/gpt-2/main.cpp
vendor/ggml/examples/gpt-2/quantize.cpp
vendor/ggml/examples/gpt-j/CMakeLists.txt
vendor/ggml/examples/gpt-j/README.md
vendor/ggml/examples/gpt-j/convert-h5-to-ggml.py
vendor/ggml/examples/gpt-j/download-ggml-model.sh
vendor/ggml/examples/gpt-j/download-model.sh
vendor/ggml/examples/gpt-j/main.cpp
vendor/ggml/examples/gpt-j/quantize.cpp
vendor/ggml/examples/whisper/CMakeLists.txt
vendor/ggml/examples/whisper/README.md
vendor/ggml/examples/whisper/convert-pt-to-ggml.py
vendor/ggml/examples/whisper/main.cpp
vendor/ggml/examples/whisper/quantize.cpp
vendor/ggml/examples/whisper/whisper.cpp
vendor/ggml/examples/whisper/whisper.h
vendor/ggml/include/ggml/ggml.h
vendor/ggml/src/CMakeLists.txt
vendor/ggml/src/ggml.c
vendor/ggml/tests/CMakeLists.txt
vendor/ggml/tests/test-blas0.c
vendor/ggml/tests/test-grad0.c
vendor/ggml/tests/test-mul-mat0.c
vendor/ggml/tests/test-mul-mat1.c
vendor/ggml/tests/test-mul-mat2.c
vendor/ggml/tests/test-svd0.c
vendor/ggml/tests/test-vec0.c
vendor/ggml/tests/test-vec1.c
vendor/ggml/tests/test-vec2.c
vendor/ggml/tests/test0.c
vendor/ggml/tests/test1.c
vendor/ggml/tests/test2.c
