Metadata-Version: 2.1
Name: ggml-python
Version: 0.0.4
Summary: Python bindings for ggml
Home-page: UNKNOWN
Author: Andrei Betlen
Author-email: abetlen@gmail.com
License: MIT
Platform: UNKNOWN
Classifier: Programming Language :: Python :: 3
Classifier: Programming Language :: Python :: 3.7
Classifier: Programming Language :: Python :: 3.8
Classifier: Programming Language :: Python :: 3.9
Classifier: Programming Language :: Python :: 3.10
Classifier: Programming Language :: Python :: 3.11
Requires-Python: >=3.7
